python_trader/__init__.py
python_trader/csv_parser.py
python_trader/df_tools.py
python_trader/indicators.py
python_trader/strategy.py
python_trader/trader.py
python_trader-1.0.0.dist-info/METADATA
python_trader-1.0.0.dist-info/WHEEL
python_trader-1.0.0.dist-info/top_level.txt
python_trader-1.0.0.dist-info/RECORD
